topsis/__init__.py
topsis/topsis.py
topsis_tanishka_102303245-1.0.1.dist-info/LICENCE
topsis_tanishka_102303245-1.0.1.dist-info/METADATA
topsis_tanishka_102303245-1.0.1.dist-info/WHEEL
topsis_tanishka_102303245-1.0.1.dist-info/entry_points.txt
topsis_tanishka_102303245-1.0.1.dist-info/top_level.txt
topsis_tanishka_102303245-1.0.1.dist-info/RECORD
