Metadata-Version: 2.1
Name: topsis-tanishka-102303245
Version: 1.0.1
Summary: TOPSIS implementation for multi-criteria decision making
Author: Tanishka
Author-email: tanishkarathee2705@gmail.com
Requires-Python: >=3.6
License-File: LICENCE
Requires-Dist: pandas
Requires-Dist: numpy
